[
    {
        "id": 1,
        "nombre": "Zapato azul",
        "precio": 5000,
        "referencia": "G40",
        "foto": "1.jpg"
    },
    {
        "id": 2,
        "nombre": "Zapato rojo",
        "precio": 5000,
        "referencia": "G40",
        "foto": "2.jpg"
    },
    {
        "id": 3,
        "nombre": "Zapato verde",
        "precio": 5000,
        "referencia": "G40",
        "foto": "3.jpg"
    },
    {
        "id": 4,
        "nombre": "Zapato gris",
        "precio": 5000,
        "referencia": "G40",
        "foto": "4.jpg"
    },
    {
        "id": 5,
        "nombre": "Zapato cafe",
        "precio": 5000,
        "referencia": "G40",
        "foto": "5.jpg"
    },
    {
        "id": 6,
        "nombre": "Zapato miel",
        "precio": 5000,
        "referencia": "G40",
        "foto": "6.jpg"
    },
    {
        "id": 7,
        "nombre": "Zapato aguamarina",
        "precio": 5000,
        "referencia": "G40",
        "foto": "7.jpg"
    },
    {
        "id": 8,
        "nombre": "Zapato piel",
        "precio": 5000,
        "referencia": "G40",
        "foto": "8.jpg"
    },
    {
        "id": 9,
        "nombre": "Zapato perla",
        "precio": 5000,
        "referencia": "G40",
        "foto": "9.jpg"
    },
    {
        "id": 10,
        "nombre": "Zapato marinado",
        "precio": 5000,
        "referencia": "G40",
        "foto": "10.jpg"
    },
    {
        "id": 11,
        "nombre": "Zapato azul1",
        "precio": 5000,
        "referencia": "G40",
        "foto": "11.jpg"
    },
    {
        "id": 12,
        "nombre": "Zapato azul2",
        "precio": 5000,
        "referencia": "G40",
        "foto": "12.jpg"
    },
    {
        "id": 13,
        "nombre": "Zapato azul3",
        "precio": 5000,
        "referencia": "G40",
        "foto": "13.jpg"
    },
    {
        "id": 14,
        "nombre": "Zapato azul4",
        "precio": 5000,
        "referencia": "G40",
        "foto": "14.jpg"
    },
    {
        "id": 15,
        "nombre": "Zapato azul5",
        "precio": 5000,
        "referencia": "G40",
        "foto": "15.jpg"
    },
    {
        "id": 16,
        "nombre": "Zapato azul6",
        "precio": 5000,
        "referencia": "G40",
        "foto": "16.jpg"
    },
    {
        "id": 17,
        "nombre": "Zapato azul7",
        "precio": 5000,
        "referencia": "G40",
        "foto": "17.jpg"
    },
    {
        "id": 18,
        "nombre": "Zapato azul8",
        "precio": 5000,
        "referencia": "G40",
        "foto": "18.jpg"
    },
    {
        "id": 19,
        "nombre": "Zapato azul9",
        "precio": 5000,
        "referencia": "G40",
        "foto": "19.jpg"
    },
    {
        "id": 20,
        "nombre": "Zapato azul10",
        "precio": 5000,
        "referencia": "G40",
        "foto": "20.jpg"
    }
]